mcai_worker_sdk-2.1.1.dist-info/METADATA
mcai_worker_sdk-2.1.1.dist-info/WHEEL
mcai_worker_sdk-2.1.1.dist-info/licenses/LICENSE
mcai_worker_sdk.libs/libssl-52849bc7.so.1.1
mcai_worker_sdk.libs/libcrypto-401bea5d.so.1.1
mcai_worker_sdk/__init__.py
mcai_worker_sdk/mcai_worker_sdk.cpython-312-x86_64-linux-gnu.so
mcai_worker_sdk-2.1.1.dist-info/RECORD
