Metadata-Version: 2.3
Name: mcai_worker_sdk
Version: 2.1.1
Requires-Dist: json-strong-typing
License-File: LICENSE
Summary: MCAI SDK to develop Python worker
Keywords: AMQP,micro-service,python
Home-Page: https://gitlab.com/media-cloud-ai/sdks/py_mcai_worker_sdk
Author: Valentin NOEL <valentin.noel@media-io.com>, Marc-Antoine Arnaud <maarnaud@media-io.com>, Thibaud Le Graverend <thibaud.legraverend@luminvent.com>, Nicolas Pierre <nico.pierre@icloud.com>
Author-email: Valentin NOEL <valentin.noel@media-io.com>, Marc-Antoine Arnaud <maarnaud@media-io.com>, Thibaud Le Graverend <thibaud.legraverend@luminvent.com>, Nicolas Pierre <nico.pierre@icloud.com>
License: MIT
Requires-Python: >=3.8
Project-URL: Documentation, https://mcai-python-sdk.readthedocs.io/
